WkLog/WkLog.py
WkLog/__init__.py
WkLog-1.0.3.dist-info/LICENSE
WkLog-1.0.3.dist-info/METADATA
WkLog-1.0.3.dist-info/WHEEL
WkLog-1.0.3.dist-info/top_level.txt
WkLog-1.0.3.dist-info/RECORD
