Metadata-Version: 2.1
Name: WkLog
Version: 1.0.3
Summary: A simple but powerful log module for Python
Home-page: https://github.com/WANGKANG1717/WkLog
Author: WANGKANG
Author-email: 1686617586@qq.com
License: LGPL-2.1
Platform: all
Classifier: Intended Audience :: Developers
Classifier: Operating System :: OS Independent
Classifier: Natural Language :: Chinese (Simplified)
Classifier: Programming Language :: Python
Classifier: Programming Language :: Python :: 3
Classifier: Programming Language :: Python :: 3.10
Classifier: Programming Language :: Python :: 3.11
Classifier: Programming Language :: Python :: 3.12
Classifier: Topic :: Software Development :: Libraries
Requires-Python: >=3.10.0
License-File: LICENSE
